pydict_filter.py
pydict_filter-0.1.7.dist-info/WHEEL
pydict_filter-0.1.7.dist-info/METADATA
pydict_filter-0.1.7.dist-info/RECORD
