Metadata-Version: 2.1
Name: pydict-filter
Version: 0.1.7
Summary: This package will help you to smart filter dictionary fields.
Home-page: https://github.com/Nextpertise/py-dict-filter
License: MIT
Author: Kamenlom
Author-email: ivashchenko.roman111@gmail.com
Requires-Python: >=3.8,<4.0
Classifier: License :: OSI Approved :: MIT License
Classifier: Programming Language :: Python :: 3
Classifier: Programming Language :: Python :: 3.8
Classifier: Programming Language :: Python :: 3.9
Classifier: Programming Language :: Python :: 3.10
Classifier: Programming Language :: Python :: 3.11
Project-URL: Repository, https://github.com/Nextpertise/py-dict-filter
